MANIFEST.in
README.md
requirements-dev.txt
requirements.txt
setup.py
sat_fetch.egg-info/PKG-INFO
sat_fetch.egg-info/SOURCES.txt
sat_fetch.egg-info/dependency_links.txt
sat_fetch.egg-info/entry_points.txt
sat_fetch.egg-info/requires.txt
sat_fetch.egg-info/top_level.txt
satfetch/__init__.py
satfetch/cli.py
satfetch/fetch.py
satfetch/version.py
test/test_cli.py
test/test_fetch.py