Metadata-Version: 1.1
Name: sat-fetch
Version: 0.1.0rc2
Summary: Fetch satellite data for AOIs
Home-page: https://github.com/sat-utils/sat-fetch
Author: Matthew Hanson
Author-email: matt.a.hanson@gmail.com
License: MIT
Platform: UNKNOWN
Classifier: Intended Audience :: Developers
Classifier: License :: OSI Approved :: MIT License
Classifier: Programming Language :: Python :: 2.7
Classifier: Programming Language :: Python :: 3.5
Classifier: Programming Language :: Python :: 3.6
